nmu/Main.py
nmu/__init__.py
nmu/code.png
nmu/py.typed
nmu/chromedriver/chromedriver_linux64/LICENSE.chromedriver
nmu/chromedriver/chromedriver_linux64/chromedriver
nmu/chromedriver/chromedriver_mac_arm64/LICENSE.chromedriver
nmu/chromedriver/chromedriver_mac_arm64/chromedriver
nmu/chromedriver/chromedriver_win32/LICENSE.chromedriver
nmu/chromedriver/chromedriver_win32/chromedriver.exe
nmu/common/Browser.py
nmu/common/CheckSystem.py
nmu/common/__init__.py
nmu/firewalldatacenter/Operation.py
nmu/firewallout/Operation.py
nmu/log/Operation.py
nmu/maxs/Operation.py
nmu/utils/HashTool.py
nmu/utils/Hasher.py
nmu/utils/PostgreSQLTool.py
nmu/utils/Verifycode.py
nmu/utils/__init__.py
nmu-0.1.5.dist-info/METADATA
nmu-0.1.5.dist-info/WHEEL
nmu-0.1.5.dist-info/RECORD
