Metadata-Version: 2.4
Name: nmu
Version: 0.1.5
Summary: Add your description here
Author-email: tyang <ytong@datav.com>
Requires-Python: >=3.10
Requires-Dist: dbutils>=3.1.0
Requires-Dist: ddddocr>=1.5.6
Requires-Dist: httpx>=0.28.1
Requires-Dist: psycopg2-binary>=2.9.10
Requires-Dist: selenium>=4.28.0
